specdirs/.DS_Store
specdirs/__init__.py
specdirs/platforms/__init__.py
specdirs/platforms/_posix.py
specdirs/platforms/macos.py
specdirs/platforms/windows.py
specdirs/py.typed
specdirs/xdg.py
specdirs-0.1.0b3.dist-info/licenses/LICENSE
specdirs-0.1.0b3.dist-info/WHEEL
specdirs-0.1.0b3.dist-info/METADATA
specdirs-0.1.0b3.dist-info/RECORD
