Metadata-Version: 2.4
Name: specdirs
Version: 0.1.0b3
Summary: Modern, composable, and specifications-compliant standard directories library
Keywords: known,folder,API,XDG,base,directory,specification,user,dirs,platform,project,app,dir
Author: Asadullah Shaikh
License-Expression: MIT
License-File: LICENSE
Classifier: Development Status :: 4 - Beta
Classifier: Intended Audience :: Developers
Classifier: Operating System :: MacOS
Classifier: Operating System :: Microsoft :: Windows
Classifier: Operating System :: POSIX
Classifier: Operating System :: POSIX :: Linux
Classifier: Programming Language :: Python :: 3
Classifier: Topic :: Software Development :: Libraries :: Python Modules
Classifier: Topic :: System :: Filesystems
Classifier: Typing :: Typed
Requires-Python: >=3.10
Project-URL: Repository, https://github.com/pantheraleo-7/specdirs
